src/decoder3x8.v
`default_nettype none

module decoder3x8 (
    input  wire       a,
    input  wire       b,
    input  wire       c,
    output wire [7:0] o
);
    assign o = 8'b00000001 << {a, b, c};
endmodule

`default_nettype wire

sim/tb_decoder3x8.sv
`timescale 1ns/1ps
`default_nettype none

module tb_decoder3x8;
    logic a;
    logic b;
    logic c;
    wire [7:0] o;

    integer n;
    integer checked;
    logic [7:0] expected;

    decoder3x8 dut (.a(a), .b(b), .c(c), .o(o));

    initial begin
        $dumpfile("wave.vcd");
        $dumpvars(0, tb_decoder3x8);
        a = 1'b0;
        b = 1'b0;
        c = 1'b0;
        checked = 0;

        for (n = 0; n < 8; n = n + 1) begin
            {a, b, c} = n[2:0];
            expected = 8'b00000001 << n;
            #10;
            if (o !== expected)
                $fatal(1,
                    "LAB1_FAIL decoder3x8 case=%0d abc=%03b expected=%08b actual=%08b",
                    n, {a, b, c}, expected, o);
            checked = checked + 1;
        end

        if (checked != 8)
            $fatal(1, "LAB1_FAIL decoder3x8 checked=%0d expected_cases=8", checked);
        $display("LAB1_PASS decoder3x8 cases=%0d", checked);
        $finish;
    end

    initial begin
        #200;
        $fatal(1, "LAB1_FAIL decoder3x8 watchdog timeout");
    end
endmodule

`default_nettype wire

evidence/decoder3x8/decoder3x8_recovery_wave.vcd
$date
   Sat Sep 12 02:32:33 2026
$end

$version
  2026.1
  $dumpfile ("wave.vcd") 
$end

$timescale
  1ps
$end

$scope module tb_decoder3x8 $end
$var reg 1 ! a $end
$var reg 1 " b $end
$var reg 1 # c $end
$var wire 8 $ o [7:0] $end
$var integer 32 % n [31:0] $end
$var integer 32 & checked [31:0] $end
$var reg 8 ' expected [7:0] $end
$scope module dut $end
$var wire 1 ( a $end
$var wire 1 ) b $end
$var wire 1 * c $end
$var wire 8 $ o [7:0] $end
$upscope $end
$upscope $end
$enddefinitions $end

#0
$dumpvars
0!
0"
0#
b1 $
b0 %
b0 &
b1 '
0(
0)
0*
$end

#10000
1#
b10 $
b1 %
b1 &
b10 '
1*

#20000
1"
0#
b100 $
b10 %
b10 &
b100 '
1)
0*

#30000
1#
b1000 $
b11 %
b11 &
b1000 '
1*

#40000
1!
0"
0#
b10000 $
b100 %
b100 &
b10000 '
1(
0)
0*

#50000
1#
b100000 $
b101 %
b101 &
b100000 '
1*

#60000
1"
0#
b1000000 $
b110 %
b110 &
b1000000 '
1)
0*

#70000
1#
b10000000 $
b111 %
b111 &
b10000000 '
1*

#80000
b1000 %
b1000 &
